examples/README.md
examples/__init__.py
examples/azure_basic.py
examples/azure_streaming.py
examples/example_decorator.py
examples/example_tracing.py
examples/getting_started.py
examples/langchain_async_examples.py
examples/openai_basic.py
examples/openai_responses.py
examples/openai_streaming.py
examples/trace_visualization_example.py
revenium_middleware_openai/__init__.py
revenium_middleware_openai/azure_config.py
revenium_middleware_openai/azure_model_resolver.py
revenium_middleware_openai/config.py
revenium_middleware_openai/exceptions.py
revenium_middleware_openai/middleware.py
revenium_middleware_openai/provider.py
revenium_middleware_openai/trace_fields.py
revenium_middleware_openai/langchain/__init__.py
revenium_middleware_openai/langchain/_utils.py
revenium_middleware_openai/langchain/unified_handler.py
revenium_middleware_openai-0.5.0.dist-info/licenses/LICENSE
revenium_middleware_openai-0.5.0.dist-info/METADATA
revenium_middleware_openai-0.5.0.dist-info/WHEEL
revenium_middleware_openai-0.5.0.dist-info/top_level.txt
revenium_middleware_openai-0.5.0.dist-info/RECORD
